glossarist/__init__.py
glossarist/cli.py
glossarist/errors.py
glossarist/utils.py
glossarist/word.py
glossarist-1.0.1.dist-info/DESCRIPTION.rst
glossarist-1.0.1.dist-info/METADATA
glossarist-1.0.1.dist-info/RECORD
glossarist-1.0.1.dist-info/WHEEL
glossarist-1.0.1.dist-info/entry_points.txt
glossarist-1.0.1.dist-info/metadata.json
glossarist-1.0.1.dist-info/top_level.txt
