Metadata-Version: 2.0
Name: glossarist
Version: 1.0.1
Summary: Assistant to write your personalised glossary
Home-page: https://github.com/kshitij10496/glossarist
Author: Kshitij Saraogi
Author-email: kshitijsaraogi@gmail.com
License: MIT
Download-URL: https://github.com/kshitij10496/glossarist/releases/tag/v1.0.0
Keywords: vocabulary command-line
Platform: UNKNOWN
Classifier: Development Status :: 3 - Alpha
Classifier: Intended Audience :: Developers
Classifier: Topic :: Software Development :: Build Tools
Classifier: License :: OSI Approved :: MIT License
Classifier: Programming Language :: Python :: 3.5
Requires-Dist: Click
Requires-Dist: arrow
Requires-Dist: python-dateutil
Requires-Dist: requests
Requires-Dist: tabulate
Requires-Dist: wordnik-py3
